Workbook
Name lstMeetingType: 'Control'!$D$2:$D$6
Name lstChannel: 'Control'!$E$2:$E$6
Name lstTimeHorizon: 'Control'!$F$2:$F$4
Name lstAssetClass: 'Control'!$G$2:$G$8
Name lstLiabilityType: 'Control'!$H$2:$H$5
Name lstPolicyType: 'Control'!$I$2:$I$7
Name lstRecommendationStatus: 'Control'!$J$2:$J$6
Name lstTaskStatus: 'Control'!$K$2:$K$7
Name lstDataQuality: 'Control'!$L$2:$L$4
Name lstYesNo: 'Control'!$M$2:$M$3
Name VAL_DATE: 'RetirementAssumptions'!$B$2
Name INFLATION: 'RetirementAssumptions'!$B$3
Name GROWTH: 'RetirementAssumptions'!$B$4
Name SWR: 'RetirementAssumptions'!$B$5

Sheet Control
A1: Adviser Transcript Schema (v1) | D1: MeetingType | E1: Channel | F1: TimeHorizon | G1: AssetClass | H1: LiabilityType | I1: PolicyType | J1: RecommendationStatus | K1: TaskStatus | L1: DataQuality | M1: YesNo
D2: Intro | E2: Zoom | F2: Short | G2: Cash | H2: Mortgage | I2: Term life | J2: Proposed | K2: Open | L2: Confirmed | M2: Yes
A3: SchemaVersion | B3: 1.0 | D3: Review | E3: Phone | F3: Medium | G3: Investment account | H3: Loan | I3: Whole life | J3: Agreed | K3: In progress | L3: Estimated | M3: No
A4: CreatedUTC | B4: 2026-01-29 14:06:09 | D4: Planning | E4: In person | F4: Long | G4: Pension | H4: Credit card | I4: Income protection | J4: Implementing | K4: Waiting on client | L4: Missing
D5: Implementation | E5: Teams | G5: Property | H5: Other | I5: Critical illness | J5: Completed | K5: Waiting on provider
A6: Reference Lists (for data validation) | D6: Admin | E6: WhatsApp | G6: Business interest | I6: Medical | J6: Rejected | K6: Completed
G7: Crypto | I7: Other | K7: Cancelled
G8: Other

Sheet RetirementAssumptions
A1: Parameter | B1: Value | C1: Notes
A2: ValuationDate | B2: 46051 | C2: Date used for age and projection calculations
A3: InflationAssumption | B3: 0.025 | C3: Annual inflation assumption
A4: NominalGrowthAssumption | B4: 0.05 | C4: Annual nominal growth assumption for invested assets
A5: WithdrawalRate | B5: 0.04 | C5: Safe withdrawal rate used to estimate required retirement pot
A6: DefaultCurrency | B6: GBP | C6: Reporting currency for retirement planning outputs

Sheet LocationPlan
A1: LocationID | B1: HouseholdID | C1: ClientID | D1: Country | E1: Probability | F1: Notes

Sheet RetirementPlan
A1: RetPlanID | B1: ClientID | C1: TargetRetirementAge | D1: TargetRetirementDate | E1: DesiredAnnualNetIncome | F1: Currency | G1: ExpectedOtherAnnualIncome | H1: ExpectedStatePensionAnnual | I1: PlannedContributionAnnual | J1: ContributionEndAge | K1: GrowthAssumptionOverride | L1: InflationOverride | M1: WithdrawalRateOverride | N1: MostLikelyRetirementCountry | O1: Notes

Sheet RetirementOutput
A1: ClientID | B1: ClientName | C1: AgeNow | D1: YearsToRetirement | E1: TargetRetirementAge | F1: ProjectedPotAtRetirement | G1: RequiredPot | H1: SurplusDeficit | I1: DesiredAnnualNetIncome | J1: OtherIncomeAtRetirement | K1: MostLikelyRetirementCountry
B2: =IF($A2="","",XLOOKUP($A2,Clients!$A:$A,Clients!$D:$D)&" "&XLOOKUP($A2,Clients!$A:$A,Clients!$E:$E)) | C2: =IF($A2="","",DATEDIF(XLOOKUP($A2,Clients!$A:$A,Clients!$F:$F),VAL_DATE,"Y")) | D2: =IF(OR($A2="",E2=""),"",E2-C2) | E2: =IF($A2="","",XLOOKUP($A2,RetirementPlan!$B:$B,RetirementPlan!$C:$C,"")) | F2: =IF(OR($A2="",D2=""),"",FV(IF(IFERROR(XLOOKUP($A2,RetirementPlan!$B:$B,RetirementPlan!$K:$K,""),"")="",GROWTH,IFERROR(XLOOKUP($A2,RetirementPlan!$B:$B,RetirementPlan!$K:$K,""),"")),D2,-N(XLOOKUP($A2,RetirementPlan!$B:$B,RetirementPlan!$I:$I,0)),-SUMIFS(Assets!$J:$J,Assets!$B:$B,$A2,Assets!$R:$R,"Yes"),0)) | G2: =IF(OR($A2="",I2=""),"",MAX(0,(I2-J2)/IF(IFERROR(XLOOKUP($A2,RetirementPlan!$B:$B,RetirementPlan!$M:$M,""),"")="",SWR,IFERROR(XLOOKUP($A2,RetirementPlan!$B:$B,RetirementPlan!$M:$M,""),"")))) | H2: =IF(OR($A2="",F2="",G2=""),"",F2-G2) | I2: =IF($A2="","",XLOOKUP($A2,RetirementPlan!$B:$B,RetirementPlan!$E:$E,"")) | J2: =IF($A2="","",N(XLOOKUP($A2,RetirementPlan!$B:$B,RetirementPlan!$G:$G,0))+N(XLOOKUP($A2,RetirementPlan!$B:$B,RetirementPlan!$H:$H,0))) | K2: =IF($A2="","",IF(NOT(ISBLANK(XLOOKUP($A2,RetirementPlan!$B:$B,RetirementPlan!$N:$N,""))),XLOOKUP($A2,RetirementPlan!$B:$B,RetirementPlan!$N:$N,""),LET(cid,$A2,c,FILTER(LocationPlan!$D:$D,LocationPlan!$C:$C=cid),p,FILTER(LocationPlan!$E:$E,LocationPlan!$C:$C=cid),IFERROR(INDEX(c,MATCH(MAX(p),p,0)),""))))
B3: =IF($A3="","",XLOOKUP($A3,Clients!$A:$A,Clients!$D:$D)&" "&XLOOKUP($A3,Clients!$A:$A,Clients!$E:$E)) | C3: =IF($A3="","",DATEDIF(XLOOKUP($A3,Clients!$A:$A,Clients!$F:$F),VAL_DATE,"Y")) | D3: =IF(OR($A3="",E3=""),"",E3-C3) | E3: =IF($A3="","",XLOOKUP($A3,RetirementPlan!$B:$B,RetirementPlan!$C:$C,"")) | F3: =IF(OR($A3="",D3=""),"",FV(IF(IFERROR(XLOOKUP($A3,RetirementPlan!$B:$B,RetirementPlan!$K:$K,""),"")="",GROWTH,IFERROR(XLOOKUP($A3,RetirementPlan!$B:$B,RetirementPlan!$K:$K,""),"")),D3,-N(XLOOKUP($A3,RetirementPlan!$B:$B,RetirementPlan!$I:$I,0)),-SUMIFS(Assets!$J:$J,Assets!$B:$B,$A3,Assets!$R:$R,"Yes"),0)) | G3: =IF(OR($A3="",I3=""),"",MAX(0,(I3-J3)/IF(IFERROR(XLOOKUP($A3,RetirementPlan!$B:$B,RetirementPlan!$M:$M,""),"")="",SWR,IFERROR(XLOOKUP($A3,RetirementPlan!$B:$B,RetirementPlan!$M:$M,""),"")))) | H3: =IF(OR($A3="",F3="",G3=""),"",F3-G3) | I3: =IF($A3="","",XLOOKUP($A3,RetirementPlan!$B:$B,RetirementPlan!$E:$E,"")) | J3: =IF($A3="","",N(XLOOKUP($A3,RetirementPlan!$B:$B,RetirementPlan!$G:$G,0))+N(XLOOKUP($A3,RetirementPlan!$B:$B,RetirementPlan!$H:$H,0))) | K3: =IF($A3="","",IF(NOT(ISBLANK(XLOOKUP($A3,RetirementPlan!$B:$B,RetirementPlan!$N:$N,""))),XLOOKUP($A3,RetirementPlan!$B:$B,RetirementPlan!$N:$N,""),LET(cid,$A3,c,FILTER(LocationPlan!$D:$D,LocationPlan!$C:$C=cid),p,FILTER(LocationPlan!$E:$E,LocationPlan!$C:$C=cid),IFERROR(INDEX(c,MATCH(MAX(p),p,0)),""))))
B4: =IF($A4="","",XLOOKUP($A4,Clients!$A:$A,Clients!$D:$D)&" "&XLOOKUP($A4,Clients!$A:$A,Clients!$E:$E)) | C4: =IF($A4="","",DATEDIF(XLOOKUP($A4,Clients!$A:$A,Clients!$F:$F),VAL_DATE,"Y")) | D4: =IF(OR($A4="",E4=""),"",E4-C4) | E4: =IF($A4="","",XLOOKUP($A4,RetirementPlan!$B:$B,RetirementPlan!$C:$C,"")) | F4: =IF(OR($A4="",D4=""),"",FV(IF(IFERROR(XLOOKUP($A4,RetirementPlan!$B:$B,RetirementPlan!$K:$K,""),"")="",GROWTH,IFERROR(XLOOKUP($A4,RetirementPlan!$B:$B,RetirementPlan!$K:$K,""),"")),D4,-N(XLOOKUP($A4,RetirementPlan!$B:$B,RetirementPlan!$I:$I,0)),-SUMIFS(Assets!$J:$J,Assets!$B:$B,$A4,Assets!$R:$R,"Yes"),0)) | G4: =IF(OR($A4="",I4=""),"",MAX(0,(I4-J4)/IF(IFERROR(XLOOKUP($A4,RetirementPlan!$B:$B,RetirementPlan!$M:$M,""),"")="",SWR,IFERROR(XLOOKUP($A4,RetirementPlan!$B:$B,RetirementPlan!$M:$M,""),"")))) | H4: =IF(OR($A4="",F4="",G4=""),"",F4-G4) | I4: =IF($A4="","",XLOOKUP($A4,RetirementPlan!$B:$B,RetirementPlan!$E:$E,"")) | J4: =IF($A4="","",N(XLOOKUP($A4,RetirementPlan!$B:$B,RetirementPlan!$G:$G,0))+N(XLOOKUP($A4,RetirementPlan!$B:$B,RetirementPlan!$H:$H,0))) | K4: =IF($A4="","",IF(NOT(ISBLANK(XLOOKUP($A4,RetirementPlan!$B:$B,RetirementPlan!$N:$N,""))),XLOOKUP($A4,RetirementPlan!$B:$B,RetirementPlan!$N:$N,""),LET(cid,$A4,c,FILTER(LocationPlan!$D:$D,LocationPlan!$C:$C=cid),p,FILTER(LocationPlan!$E:$E,LocationPlan!$C:$C=cid),IFERROR(INDEX(c,MATCH(MAX(p),p,0)),""))))
B5: =IF($A5="","",XLOOKUP($A5,Clients!$A:$A,Clients!$D:$D)&" "&XLOOKUP($A5,Clients!$A:$A,Clients!$E:$E)) | C5: =IF($A5="","",DATEDIF(XLOOKUP($A5,Clients!$A:$A,Clients!$F:$F),VAL_DATE,"Y")) | D5: =IF(OR($A5="",E5=""),"",E5-C5) | E5: =IF($A5="","",XLOOKUP($A5,RetirementPlan!$B:$B,RetirementPlan!$C:$C,"")) | F5: =IF(OR($A5="",D5=""),"",FV(IF(IFERROR(XLOOKUP($A5,RetirementPlan!$B:$B,RetirementPlan!$K:$K,""),"")="",GROWTH,IFERROR(XLOOKUP($A5,RetirementPlan!$B:$B,RetirementPlan!$K:$K,""),"")),D5,-N(XLOOKUP($A5,RetirementPlan!$B:$B,RetirementPlan!$I:$I,0)),-SUMIFS(Assets!$J:$J,Assets!$B:$B,$A5,Assets!$R:$R,"Yes"),0)) | G5: =IF(OR($A5="",I5=""),"",MAX(0,(I5-J5)/IF(IFERROR(XLOOKUP($A5,RetirementPlan!$B:$B,RetirementPlan!$M:$M,""),"")="",SWR,IFERROR(XLOOKUP($A5,RetirementPlan!$B:$B,RetirementPlan!$M:$M,""),"")))) | H5: =IF(OR($A5="",F5="",G5=""),"",F5-G5) | I5: =IF($A5="","",XLOOKUP($A5,RetirementPlan!$B:$B,RetirementPlan!$E:$E,"")) | J5: =IF($A5="","",N(XLOOKUP($A5,RetirementPlan!$B:$B,RetirementPlan!$G:$G,0))+N(XLOOKUP($A5,RetirementPlan!$B:$B,RetirementPlan!$H:$H,0))) | K5: =IF($A5="","",IF(NOT(ISBLANK(XLOOKUP($A5,RetirementPlan!$B:$B,RetirementPlan!$N:$N,""))),XLOOKUP($A5,RetirementPlan!$B:$B,RetirementPlan!$N:$N,""),LET(cid,$A5,c,FILTER(LocationPlan!$D:$D,LocationPlan!$C:$C=cid),p,FILTER(LocationPlan!$E:$E,LocationPlan!$C:$C=cid),IFERROR(INDEX(c,MATCH(MAX(p),p,0)),""))))
B6: =IF($A6="","",XLOOKUP($A6,Clients!$A:$A,Clients!$D:$D)&" "&XLOOKUP($A6,Clients!$A:$A,Clients!$E:$E)) | C6: =IF($A6="","",DATEDIF(XLOOKUP($A6,Clients!$A:$A,Clients!$F:$F),VAL_DATE,"Y")) | D6: =IF(OR($A6="",E6=""),"",E6-C6) | E6: =IF($A6="","",XLOOKUP($A6,RetirementPlan!$B:$B,RetirementPlan!$C:$C,"")) | F6: =IF(OR($A6="",D6=""),"",FV(IF(IFERROR(XLOOKUP($A6,RetirementPlan!$B:$B,RetirementPlan!$K:$K,""),"")="",GROWTH,IFERROR(XLOOKUP($A6,RetirementPlan!$B:$B,RetirementPlan!$K:$K,""),"")),D6,-N(XLOOKUP($A6,RetirementPlan!$B:$B,RetirementPlan!$I:$I,0)),-SUMIFS(Assets!$J:$J,Assets!$B:$B,$A6,Assets!$R:$R,"Yes"),0)) | G6: =IF(OR($A6="",I6=""),"",MAX(0,(I6-J6)/IF(IFERROR(XLOOKUP($A6,RetirementPlan!$B:$B,RetirementPlan!$M:$M,""),"")="",SWR,IFERROR(XLOOKUP($A6,RetirementPlan!$B:$B,RetirementPlan!$M:$M,""),"")))) | H6: =IF(OR($A6="",F6="",G6=""),"",F6-G6) | I6: =IF($A6="","",XLOOKUP($A6,RetirementPlan!$B:$B,RetirementPlan!$E:$E,"")) | J6: =IF($A6="","",N(XLOOKUP($A6,RetirementPlan!$B:$B,RetirementPlan!$G:$G,0))+N(XLOOKUP($A6,RetirementPlan!$B:$B,RetirementPlan!$H:$H,0))) | K6: =IF($A6="","",IF(NOT(ISBLANK(XLOOKUP($A6,RetirementPlan!$B:$B,RetirementPlan!$N:$N,""))),XLOOKUP($A6,RetirementPlan!$B:$B,RetirementPlan!$N:$N,""),LET(cid,$A6,c,FILTER(LocationPlan!$D:$D,LocationPlan!$C:$C=cid),p,FILTER(LocationPlan!$E:$E,LocationPlan!$C:$C=cid),IFERROR(INDEX(c,MATCH(MAX(p),p,0)),""))))
B7: =IF($A7="","",XLOOKUP($A7,Clients!$A:$A,Clients!$D:$D)&" "&XLOOKUP($A7,Clients!$A:$A,Clients!$E:$E)) | C7: =IF($A7="","",DATEDIF(XLOOKUP($A7,Clients!$A:$A,Clients!$F:$F),VAL_DATE,"Y")) | D7: =IF(OR($A7="",E7=""),"",E7-C7) | E7: =IF($A7="","",XLOOKUP($A7,RetirementPlan!$B:$B,RetirementPlan!$C:$C,"")) | F7: =IF(OR($A7="",D7=""),"",FV(IF(IFERROR(XLOOKUP($A7,RetirementPlan!$B:$B,RetirementPlan!$K:$K,""),"")="",GROWTH,IFERROR(XLOOKUP($A7,RetirementPlan!$B:$B,RetirementPlan!$K:$K,""),"")),D7,-N(XLOOKUP($A7,RetirementPlan!$B:$B,RetirementPlan!$I:$I,0)),-SUMIFS(Assets!$J:$J,Assets!$B:$B,$A7,Assets!$R:$R,"Yes"),0)) | G7: =IF(OR($A7="",I7=""),"",MAX(0,(I7-J7)/IF(IFERROR(XLOOKUP($A7,RetirementPlan!$B:$B,RetirementPlan!$M:$M,""),"")="",SWR,IFERROR(XLOOKUP($A7,RetirementPlan!$B:$B,RetirementPlan!$M:$M,""),"")))) | H7: =IF(OR($A7="",F7="",G7=""),"",F7-G7) | I7: =IF($A7="","",XLOOKUP($A7,RetirementPlan!$B:$B,RetirementPlan!$E:$E,"")) | J7: =IF($A7="","",N(XLOOKUP($A7,RetirementPlan!$B:$B,RetirementPlan!$G:$G,0))+N(XLOOKUP($A7,RetirementPlan!$B:$B,RetirementPlan!$H:$H,0))) | K7: =IF($A7="","",IF(NOT(ISBLANK(XLOOKUP($A7,RetirementPlan!$B:$B,RetirementPlan!$N:$N,""))),XLOOKUP($A7,RetirementPlan!$B:$B,RetirementPlan!$N:$N,""),LET(cid,$A7,c,FILTER(LocationPlan!$D:$D,LocationPlan!$C:$C=cid),p,FILTER(LocationPlan!$E:$E,LocationPlan!$C:$C=cid),IFERROR(INDEX(c,MATCH(MAX(p),p,0)),""))))
B8: =IF($A8="","",XLOOKUP($A8,Clients!$A:$A,Clients!$D:$D)&" "&XLOOKUP($A8,Clients!$A:$A,Clients!$E:$E)) | C8: =IF($A8="","",DATEDIF(XLOOKUP($A8,Clients!$A:$A,Clients!$F:$F),VAL_DATE,"Y")) | D8: =IF(OR($A8="",E8=""),"",E8-C8) | E8: =IF($A8="","",XLOOKUP($A8,RetirementPlan!$B:$B,RetirementPlan!$C:$C,"")) | F8: =IF(OR($A8="",D8=""),"",FV(IF(IFERROR(XLOOKUP($A8,RetirementPlan!$B:$B,RetirementPlan!$K:$K,""),"")="",GROWTH,IFERROR(XLOOKUP($A8,RetirementPlan!$B:$B,RetirementPlan!$K:$K,""),"")),D8,-N(XLOOKUP($A8,RetirementPlan!$B:$B,RetirementPlan!$I:$I,0)),-SUMIFS(Assets!$J:$J,Assets!$B:$B,$A8,Assets!$R:$R,"Yes"),0)) | G8: =IF(OR($A8="",I8=""),"",MAX(0,(I8-J8)/IF(IFERROR(XLOOKUP($A8,RetirementPlan!$B:$B,RetirementPlan!$M:$M,""),"")="",SWR,IFERROR(XLOOKUP($A8,RetirementPlan!$B:$B,RetirementPlan!$M:$M,""),"")))) | H8: =IF(OR($A8="",F8="",G8=""),"",F8-G8) | I8: =IF($A8="","",XLOOKUP($A8,RetirementPlan!$B:$B,RetirementPlan!$E:$E,"")) | J8: =IF($A8="","",N(XLOOKUP($A8,RetirementPlan!$B:$B,RetirementPlan!$G:$G,0))+N(XLOOKUP($A8,RetirementPlan!$B:$B,RetirementPlan!$H:$H,0))) | K8: =IF($A8="","",IF(NOT(ISBLANK(XLOOKUP($A8,RetirementPlan!$B:$B,RetirementPlan!$N:$N,""))),XLOOKUP($A8,RetirementPlan!$B:$B,RetirementPlan!$N:$N,""),LET(cid,$A8,c,FILTER(LocationPlan!$D:$D,LocationPlan!$C:$C=cid),p,FILTER(LocationPlan!$E:$E,LocationPlan!$C:$C=cid),IFERROR(INDEX(c,MATCH(MAX(p),p,0)),""))))
B9: =IF($A9="","",XLOOKUP($A9,Clients!$A:$A,Clients!$D:$D)&" "&XLOOKUP($A9,Clients!$A:$A,Clients!$E:$E)) | C9: =IF($A9="","",DATEDIF(XLOOKUP($A9,Clients!$A:$A,Clients!$F:$F),VAL_DATE,"Y")) | D9: =IF(OR($A9="",E9=""),"",E9-C9) | E9: =IF($A9="","",XLOOKUP($A9,RetirementPlan!$B:$B,RetirementPlan!$C:$C,"")) | F9: =IF(OR($A9="",D9=""),"",FV(IF(IFERROR(XLOOKUP($A9,RetirementPlan!$B:$B,RetirementPlan!$K:$K,""),"")="",GROWTH,IFERROR(XLOOKUP($A9,RetirementPlan!$B:$B,RetirementPlan!$K:$K,""),"")),D9,-N(XLOOKUP($A9,RetirementPlan!$B:$B,RetirementPlan!$I:$I,0)),-SUMIFS(Assets!$J:$J,Assets!$B:$B,$A9,Assets!$R:$R,"Yes"),0)) | G9: =IF(OR($A9="",I9=""),"",MAX(0,(I9-J9)/IF(IFERROR(XLOOKUP($A9,RetirementPlan!$B:$B,RetirementPlan!$M:$M,""),"")="",SWR,IFERROR(XLOOKUP($A9,RetirementPlan!$B:$B,RetirementPlan!$M:$M,""),"")))) | H9: =IF(OR($A9="",F9="",G9=""),"",F9-G9) | I9: =IF($A9="","",XLOOKUP($A9,RetirementPlan!$B:$B,RetirementPlan!$E:$E,"")) | J9: =IF($A9="","",N(XLOOKUP($A9,RetirementPlan!$B:$B,RetirementPlan!$G:$G,0))+N(XLOOKUP($A9,RetirementPlan!$B:$B,RetirementPlan!$H:$H,0))) | K9: =IF($A9="","",IF(NOT(ISBLANK(XLOOKUP($A9,RetirementPlan!$B:$B,RetirementPlan!$N:$N,""))),XLOOKUP($A9,RetirementPlan!$B:$B,RetirementPlan!$N:$N,""),LET(cid,$A9,c,FILTER(LocationPlan!$D:$D,LocationPlan!$C:$C=cid),p,FILTER(LocationPlan!$E:$E,LocationPlan!$C:$C=cid),IFERROR(INDEX(c,MATCH(MAX(p),p,0)),""))))
B10: =IF($A10="","",XLOOKUP($A10,Clients!$A:$A,Clients!$D:$D)&" "&XLOOKUP($A10,Clients!$A:$A,Clients!$E:$E)) | C10: =IF($A10="","",DATEDIF(XLOOKUP($A10,Clients!$A:$A,Clients!$F:$F),VAL_DATE,"Y")) | D10: =IF(OR($A10="",E10=""),"",E10-C10) | E10: =IF($A10="","",XLOOKUP($A10,RetirementPlan!$B:$B,RetirementPlan!$C:$C,"")) | F10: =IF(OR($A10="",D10=""),"",FV(IF(IFERROR(XLOOKUP($A10,RetirementPlan!$B:$B,RetirementPlan!$K:$K,""),"")="",GROWTH,IFERROR(XLOOKUP($A10,RetirementPlan!$B:$B,RetirementPlan!$K:$K,""),"")),D10,-N(XLOOKUP($A10,RetirementPlan!$B:$B,RetirementPlan!$I:$I,0)),-SUMIFS(Assets!$J:$J,Assets!$B:$B,$A10,Assets!$R:$R,"Yes"),0)) | G10: =IF(OR($A10="",I10=""),"",MAX(0,(I10-J10)/IF(IFERROR(XLOOKUP($A10,RetirementPlan!$B:$B,RetirementPlan!$M:$M,""),"")="",SWR,IFERROR(XLOOKUP($A10,RetirementPlan!$B:$B,RetirementPlan!$M:$M,""),"")))) | H10: =IF(OR($A10="",F10="",G10=""),"",F10-G10) | I10: =IF($A10="","",XLOOKUP($A10,RetirementPlan!$B:$B,RetirementPlan!$E:$E,"")) | J10: =IF($A10="","",N(XLOOKUP($A10,RetirementPlan!$B:$B,RetirementPlan!$G:$G,0))+N(XLOOKUP($A10,RetirementPlan!$B:$B,RetirementPlan!$H:$H,0))) | K10: =IF($A10="","",IF(NOT(ISBLANK(XLOOKUP($A10,RetirementPlan!$B:$B,RetirementPlan!$N:$N,""))),XLOOKUP($A10,RetirementPlan!$B:$B,RetirementPlan!$N:$N,""),LET(cid,$A10,c,FILTER(LocationPlan!$D:$D,LocationPlan!$C:$C=cid),p,FILTER(LocationPlan!$E:$E,LocationPlan!$C:$C=cid),IFERROR(INDEX(c,MATCH(MAX(p),p,0)),""))))
B11: =IF($A11="","",XLOOKUP($A11,Clients!$A:$A,Clients!$D:$D)&" "&XLOOKUP($A11,Clients!$A:$A,Clients!$E:$E)) | C11: =IF($A11="","",DATEDIF(XLOOKUP($A11,Clients!$A:$A,Clients!$F:$F),VAL_DATE,"Y")) | D11: =IF(OR($A11="",E11=""),"",E11-C11) | E11: =IF($A11="","",XLOOKUP($A11,RetirementPlan!$B:$B,RetirementPlan!$C:$C,"")) | F11: =IF(OR($A11="",D11=""),"",FV(IF(IFERROR(XLOOKUP($A11,RetirementPlan!$B:$B,RetirementPlan!$K:$K,""),"")="",GROWTH,IFERROR(XLOOKUP($A11,RetirementPlan!$B:$B,RetirementPlan!$K:$K,""),"")),D11,-N(XLOOKUP($A11,RetirementPlan!$B:$B,RetirementPlan!$I:$I,0)),-SUMIFS(Assets!$J:$J,Assets!$B:$B,$A11,Assets!$R:$R,"Yes"),0)) | G11: =IF(OR($A11="",I11=""),"",MAX(0,(I11-J11)/IF(IFERROR(XLOOKUP($A11,RetirementPlan!$B:$B,RetirementPlan!$M:$M,""),"")="",SWR,IFERROR(XLOOKUP($A11,RetirementPlan!$B:$B,RetirementPlan!$M:$M,""),"")))) | H11: =IF(OR($A11="",F11="",G11=""),"",F11-G11) | I11: =IF($A11="","",XLOOKUP($A11,RetirementPlan!$B:$B,RetirementPlan!$E:$E,"")) | J11: =IF($A11="","",N(XLOOKUP($A11,RetirementPlan!$B:$B,RetirementPlan!$G:$G,0))+N(XLOOKUP($A11,RetirementPlan!$B:$B,RetirementPlan!$H:$H,0))) | K11: =IF($A11="","",IF(NOT(ISBLANK(XLOOKUP($A11,RetirementPlan!$B:$B,RetirementPlan!$N:$N,""))),XLOOKUP($A11,RetirementPlan!$B:$B,RetirementPlan!$N:$N,""),LET(cid,$A11,c,FILTER(LocationPlan!$D:$D,LocationPlan!$C:$C=cid),p,FILTER(LocationPlan!$E:$E,LocationPlan!$C:$C=cid),IFERROR(INDEX(c,MATCH(MAX(p),p,0)),""))))
B12: =IF($A12="","",XLOOKUP($A12,Clients!$A:$A,Clients!$D:$D)&" "&XLOOKUP($A12,Clients!$A:$A,Clients!$E:$E)) | C12: =IF($A12="","",DATEDIF(XLOOKUP($A12,Clients!$A:$A,Clients!$F:$F),VAL_DATE,"Y")) | D12: =IF(OR($A12="",E12=""),"",E12-C12) | E12: =IF($A12="","",XLOOKUP($A12,RetirementPlan!$B:$B,RetirementPlan!$C:$C,"")) | F12: =IF(OR($A12="",D12=""),"",FV(IF(IFERROR(XLOOKUP($A12,RetirementPlan!$B:$B,RetirementPlan!$K:$K,""),"")="",GROWTH,IFERROR(XLOOKUP($A12,RetirementPlan!$B:$B,RetirementPlan!$K:$K,""),"")),D12,-N(XLOOKUP($A12,RetirementPlan!$B:$B,RetirementPlan!$I:$I,0)),-SUMIFS(Assets!$J:$J,Assets!$B:$B,$A12,Assets!$R:$R,"Yes"),0)) | G12: =IF(OR($A12="",I12=""),"",MAX(0,(I12-J12)/IF(IFERROR(XLOOKUP($A12,RetirementPlan!$B:$B,RetirementPlan!$M:$M,""),"")="",SWR,IFERROR(XLOOKUP($A12,RetirementPlan!$B:$B,RetirementPlan!$M:$M,""),"")))) | H12: =IF(OR($A12="",F12="",G12=""),"",F12-G12) | I12: =IF($A12="","",XLOOKUP($A12,RetirementPlan!$B:$B,RetirementPlan!$E:$E,"")) | J12: =IF($A12="","",N(XLOOKUP($A12,RetirementPlan!$B:$B,RetirementPlan!$G:$G,0))+N(XLOOKUP($A12,RetirementPlan!$B:$B,RetirementPlan!$H:$H,0))) | K12: =IF($A12="","",IF(NOT(ISBLANK(XLOOKUP($A12,RetirementPlan!$B:$B,RetirementPlan!$N:$N,""))),XLOOKUP($A12,RetirementPlan!$B:$B,RetirementPlan!$N:$N,""),LET(cid,$A12,c,FILTER(LocationPlan!$D:$D,LocationPlan!$C:$C=cid),p,FILTER(LocationPlan!$E:$E,LocationPlan!$C:$C=cid),IFERROR(INDEX(c,MATCH(MAX(p),p,0)),""))))
B13: =IF($A13="","",XLOOKUP($A13,Clients!$A:$A,Clients!$D:$D)&" "&XLOOKUP($A13,Clients!$A:$A,Clients!$E:$E)) | C13: =IF($A13="","",DATEDIF(XLOOKUP($A13,Clients!$A:$A,Clients!$F:$F),VAL_DATE,"Y")) | D13: =IF(OR($A13="",E13=""),"",E13-C13) | E13: =IF($A13="","",XLOOKUP($A13,RetirementPlan!$B:$B,RetirementPlan!$C:$C,"")) | F13: =IF(OR($A13="",D13=""),"",FV(IF(IFERROR(XLOOKUP($A13,RetirementPlan!$B:$B,RetirementPlan!$K:$K,""),"")="",GROWTH,IFERROR(XLOOKUP($A13,RetirementPlan!$B:$B,RetirementPlan!$K:$K,""),"")),D13,-N(XLOOKUP($A13,RetirementPlan!$B:$B,RetirementPlan!$I:$I,0)),-SUMIFS(Assets!$J:$J,Assets!$B:$B,$A13,Assets!$R:$R,"Yes"),0)) | G13: =IF(OR($A13="",I13=""),"",MAX(0,(I13-J13)/IF(IFERROR(XLOOKUP($A13,RetirementPlan!$B:$B,RetirementPlan!$M:$M,""),"")="",SWR,IFERROR(XLOOKUP($A13,RetirementPlan!$B:$B,RetirementPlan!$M:$M,""),"")))) | H13: =IF(OR($A13="",F13="",G13=""),"",F13-G13) | I13: =IF($A13="","",XLOOKUP($A13,RetirementPlan!$B:$B,RetirementPlan!$E:$E,"")) | J13: =IF($A13="","",N(XLOOKUP($A13,RetirementPlan!$B:$B,RetirementPlan!$G:$G,0))+N(XLOOKUP($A13,RetirementPlan!$B:$B,RetirementPlan!$H:$H,0))) | K13: =IF($A13="","",IF(NOT(ISBLANK(XLOOKUP($A13,RetirementPlan!$B:$B,RetirementPlan!$N:$N,""))),XLOOKUP($A13,RetirementPlan!$B:$B,RetirementPlan!$N:$N,""),LET(cid,$A13,c,FILTER(LocationPlan!$D:$D,LocationPlan!$C:$C=cid),p,FILTER(LocationPlan!$E:$E,LocationPlan!$C:$C=cid),IFERROR(INDEX(c,MATCH(MAX(p),p,0)),""))))
... B501: =IF($A501="","",XLOOKUP($A501,Clients!$A:$A,Clients!$D:$D)&" "&XLOOKUP($A501,Clients!$A:$A,Clients!$E:$E)) | C501: =IF($A501="","",DATEDIF(XLOOKUP($A501,Clients!$A:$A,Clients!$F:$F),VAL_DATE,"Y")) | D501: =IF(OR($A501="",E501=""),"",E501-C501) | E501: =IF($A501="","",XLOOKUP($A501,RetirementPlan!$B:$B,RetirementPlan!$C:$C,"")) | F501: =IF(OR($A501="",D501=""),"",FV(IF(IFERROR(XLOOKUP($A501,RetirementPlan!$B:$B,RetirementPlan!$K:$K,""),"")="",GROWTH,IFERROR(XLOOKUP($A501,RetirementPlan!$B:$B,RetirementPlan!$K:$K,""),"")),D501,-N(XLOOKUP($A501,RetirementPlan!$B:$B,RetirementPlan!$I:$I,0)),-SUMIFS(Assets!$J:$J,Assets!$B:$B,$A501,Assets!$R:$R,"Yes"),0)) | G501: =IF(OR($A501="",I501=""),"",MAX(0,(I501-J501)/IF(IFERROR(XLOOKUP($A501,RetirementPlan!$B:$B,RetirementPlan!$M:$M,""),"")="",SWR,IFERROR(XLOOKUP($A501,RetirementPlan!$B:$B,RetirementPlan!$M:$M,""),"")))) | H501: =IF(OR($A501="",F501="",G501=""),"",F501-G501) | I501: =IF($A501="","",XLOOKUP($A501,RetirementPlan!$B:$B,RetirementPlan!$E:$E,"")) | J501: =IF($A501="","",N(XLOOKUP($A501,RetirementPlan!$B:$B,RetirementPlan!$G:$G,0))+N(XLOOKUP($A501,RetirementPlan!$B:$B,RetirementPlan!$H:$H,0))) | K501: =IF($A501="","",IF(NOT(ISBLANK(XLOOKUP($A501,RetirementPlan!$B:$B,RetirementPlan!$N:$N,""))),XLOOKUP($A501,RetirementPlan!$B:$B,RetirementPlan!$N:$N,""),LET(cid,$A501,c,FILTER(LocationPlan!$D:$D,LocationPlan!$C:$C=cid),p,FILTER(LocationPlan!$E:$E,LocationPlan!$C:$C=cid),IFERROR(INDEX(c,MATCH(MAX(p),p,0)),""))))

Sheet Meetings
A1: MeetingID | B1: MeetingDateTime | C1: Adviser | D1: MeetingType | E1: Channel | F1: RecordingLink | G1: TranscriptFileName | H1: Participants | I1: HouseholdID | J1: PrimaryClientID | K1: SecondaryClientID | L1: MeetingOutcomeSummary | M1: NextMeetingProposed

Sheet Households
A1: HouseholdID | B1: HouseholdName | C1: CountryOfResidence | D1: TaxResidencySummary | E1: Notes

Sheet Clients
A1: ClientID | B1: HouseholdID | C1: Title | D1: FirstName | E1: LastName | F1: DOB | G1: Nationality | H1: ResidencyCountry | I1: Domicile | J1: MaritalStatus | K1: DependantsCount | L1: EmploymentStatus | M1: EmployerName | N1: RoleTitle | O1: IncomeGrossAnnual | P1: IncomeNetAnnual | Q1: Currency | R1: ContactEmail | S1: Phone | T1: PreferredContactMethod | U1: RiskProfileStated | V1: CapacityForLossIndicator | W1: ConfirmationStatus | X1: Notes

Sheet Goals
A1: GoalID | B1: HouseholdID | C1: ClientID | D1: GoalCategory | E1: GoalDescription | F1: TimeHorizon | G1: TargetDate | H1: TargetAmount | I1: Currency | J1: Priority(1-5) | K1: Constraints | L1: SuccessDefinition

Sheet Income
A1: IncomeID | B1: ClientID | C1: SourceType | D1: Amount | E1: Frequency | F1: Currency | G1: IsGuaranteed | H1: StartDate | I1: EndDate | J1: TaxedWhere | K1: Notes

Sheet Assets
A1: AssetID | B1: ClientID | C1: AssetClass | D1: Provider | E1: Platform | F1: AccountName | G1: AccountNumberLast4 | H1: CountryHeld | I1: Currency | J1: CurrentValue | K1: CostBasis | L1: ContributionType | M1: RegularContributionAmount | N1: RegularContributionFrequency | O1: OwnershipSplit | P1: Notes | Q1: DataQuality | R1: IncludeInRetirementPlan

Sheet Holdings
A1: HoldingID | B1: AssetID | C1: ISIN | D1: Ticker | E1: FundName | F1: AssetType | G1: Region | H1: Sector | I1: RiskCategory | J1: Units | K1: Price | L1: MarketValue | M1: OCF | N1: PlatformFee | O1: AdviserFee | P1: TotalEstimatedFee | Q1: Notes

Sheet Pensions
A1: PensionID | B1: AssetID | C1: SchemeType | D1: SchemeName | E1: Provider | F1: StartDate | G1: NormalRetirementAge | H1: CurrentValue | I1: ContributionAmount | J1: ContributionFrequency | K1: EmployerContrib | L1: ProtectedAgesOrProtections | M1: LTA_LSA_Notes | N1: BeneficiaryNominationStatus | O1: KnownTaxIssues | P1: Notes

Sheet Properties
A1: PropertyID | B1: AssetID | C1: Country | D1: Address | E1: PropertyType | F1: Ownership | G1: PurchaseDate | H1: PurchasePrice | I1: CurrentValue | J1: MortgageLinkedLiabilityID | K1: RentalIncomeGross | L1: RentalExpenses | M1: NetYield | N1: Notes

Sheet Liabilities
A1: LiabilityID | B1: ClientID | C1: Type | D1: Provider | E1: Currency | F1: Balance | G1: InterestRate | H1: RepaymentAmount | I1: RepaymentFrequency | J1: TermEndDate | K1: IsFixedOrVariable | L1: SecuredAgainstPropertyID | M1: Notes

Sheet Insurance
A1: PolicyID | B1: ClientID | C1: PolicyType | D1: Provider | E1: CoverAmount | F1: Premium | G1: Frequency | H1: Currency | I1: StartDate | J1: ReviewDate | K1: Beneficiaries | L1: LinkedGoalID | M1: Notes

Sheet TaxResidency
A1: TaxRecordID | B1: ClientID | C1: Country | D1: TaxResidencyStatus | E1: DateFrom | F1: DateTo | G1: RelevantRulesDiscussed | H1: PlanningOpportunities | I1: RisksOrRedFlags | J1: Notes

Sheet Recommendations
A1: RecID | B1: MeetingID | C1: ClientID | D1: HouseholdID | E1: RecommendationType | F1: ProductOrProvider | G1: Rationale | H1: Benefits | I1: Drawbacks | J1: FeesSummary | K1: Status | L1: TargetDate | M1: Dependencies | N1: Notes

Sheet Tasks
A1: TaskID | B1: MeetingID | C1: Owner | D1: TaskCategory | E1: TaskDescription | F1: DueDate | G1: Status | H1: BlockingIssue | I1: RelatedEntityType | J1: RelatedEntityID | K1: Notes

Sheet TranscriptEvidence
A1: EvidenceID | B1: MeetingID | C1: Speaker | D1: TimestampApprox | E1: Snippet | F1: ExtractedFieldName | G1: ExtractedValue | H1: TargetTable | I1: TargetRecordID | J1: Confidence(0-1) | K1: NeedsConfirmation(Yes/No)

Sheet MissingData
A1: GapID | B1: MeetingID | C1: ClientID | D1: MissingField | E1: WhyNeeded | F1: Priority | G1: QuestionToAskClient | H1: Status | I1: Notes

Sheet BalanceSheetSummary
A1: ClientID | B1: TotalAssets | C1: TotalLiabilities | D1: NetWorth | E1: LiquidAssets
B2: =IF($A2="","",SUMIF(Assets!$B$2:$B$500,$A2,Assets!$J$2:$J$500)) | C2: =IF($A2="","",SUMIF(Liabilities!$B$2:$B$500,$A2,Liabilities!$F$2:$F$500)) | D2: =IF($A2="","",$B2-$C2) | E2: =IF($A2="","",SUMIFS(Assets!$J$2:$J$500,Assets!$B$2:$B$500,$A2,Assets!$C$2:$C$500,"Cash")+SUMIFS(Assets!$J$2:$J$500,Assets!$B$2:$B$500,$A2,Assets!$C$2:$C$500,"Investment account"))

Sheet Retirement_Projection
A1: HouseholdID | B1: ClientID | C1: CurrentAge | D1: TargetRetirementAge | E1: LifeExpectancy | F1: CurrentInvestableAssets | G1: AnnualContribution | H1: RealReturnAssumption | I1: RetirementIncomeTarget | J1: InflationAssumption | K1: ProjectedPotAtRetirement | L1: SustainableIncome_4pct | M1: FundingGapOrSurplus | N1: PrimaryRetirementCountry | O1: Confidence
K2: =IF(AND(C2<>"",D2<>"",F2<>"",H2<>""),F2*(1+H2)^(D2-C2),"") | L2: =IF(K2<>"",K2*0.04,"") | M2: =IF(AND(L2<>"",I2<>""),L2-I2,"")

Sheet Residency_Scenarios
A1: ScenarioID | B1: HouseholdID | C1: Country | D1: StartAge | E1: EndAge | F1: Probability | G1: TaxRegimeNotes | H1: HealthcareAssumption | I1: CostOfLivingIndex | J1: NetIncomeMultiplier | K1: Notes

Sheet Retirement_By_Scenario
A1: ScenarioID | B1: HouseholdID | C1: ProjectedPotAtRetirement | D1: AfterTaxIncomeEstimate | E1: RealIncomeAdj | F1: ResultComment
